qelrix_cli/__init__.py
qelrix_cli/cli.py
qelrix_cli-0.5.0.dist-info/METADATA
qelrix_cli-0.5.0.dist-info/WHEEL
qelrix_cli-0.5.0.dist-info/entry_points.txt
qelrix_cli-0.5.0.dist-info/top_level.txt
qelrix_cli-0.5.0.dist-info/RECORD
