Metadata-Version: 2.4
Name: qelrix-cli
Version: 0.5.0
Summary: A command-line interface for interacting with Gemini AI.
Home-page: https://github.com/yourusername/qelrix-cli
Author: Your Name
Author-email: your.email@example.com
Classifier: Programming Language :: Python :: 3
Classifier: License :: OSI Approved :: MIT License
Classifier: Operating System :: OS Independent
Requires-Dist: requests
Requires-Dist: rich
Requires-Dist: pyperclip
Dynamic: author
Dynamic: author-email
Dynamic: classifier
Dynamic: description
Dynamic: description-content-type
Dynamic: home-page
Dynamic: requires-dist
Dynamic: summary
